cheapchocolate/__init__.py
cheapchocolate/__main__.py
cheapchocolate/core/config.py
cheapchocolate/core/config_files.py
cheapchocolate/core/default_files/config.yaml
cheapchocolate/core/default_files/mail_folders.yaml
cheapchocolate/modules/imap.py
cheapchocolate/modules/mailbox.py
cheapchocolate-0.4.2.dist-info/WHEEL
cheapchocolate-0.4.2.dist-info/entry_points.txt
cheapchocolate-0.4.2.dist-info/METADATA
cheapchocolate-0.4.2.dist-info/RECORD
