Metadata-Version: 2.4
Name: cheapchocolate
Version: 0.4.2
Summary: CheapChocolate is an simple imap client to receive you daily email.
Author: Cesar Cardoso
Author-email: Cesar Cardoso <hello@cesarcardoso.cc>
License-Expression: MIT
Requires-Dist: dotenv>=0.9.9
Requires-Dist: pyyaml>=6.0.3
Requires-Python: >=3.11
Project-URL: Changelog, https://github.com/bouli/cheapchocolate/releases/latest
Project-URL: Repository, https://github.com/bouli/cheapchocolate
